toggl_api_bill_generator/__init__.py
toggl_api_bill_generator/main_constants.py
toggl_api_bill_generator/toggl_constants.py
toggl_invoice_generator/__init__.py
toggl_invoice_generator/main.py
toggl_invoice_generator/toggl-invoice-generator
toggl_invoice_generator/toggl_constants.py
toggl_invoice_generator/templates/invoice.html
toggl_invoice_generator-1.0.0.data/scripts/toggl-bill-gen
toggl_invoice_generator-1.0.0.data/scripts/toggl-gen
toggl_invoice_generator-1.0.0.data/scripts/toggl-invoice-generator
toggl_invoice_generator-1.0.0.dist-info/LICENSE
toggl_invoice_generator-1.0.0.dist-info/METADATA
toggl_invoice_generator-1.0.0.dist-info/WHEEL
toggl_invoice_generator-1.0.0.dist-info/top_level.txt
toggl_invoice_generator-1.0.0.dist-info/RECORD
