Metadata-Version: 2.1
Name: toggl-invoice-generator
Version: 1.0.0
Summary: A script that will generate a PDF from Toggl.com API. Easy to automate from CRON or use from
Requires-Dist: aiofiles (==0.4.0)
Requires-Dist: aiohttp (==3.4.4)
Requires-Dist: uvloop (==0.11.2)
Requires-Dist: Jinja2 (==2.10)
Requires-Dist: pyppeteer (==0.0.25)
